My_Core133/Manager
My_Core133/auth
