Metadata-Version: 2.1
Name: My-Core133
Version: 1.5
Summary: My_Core133 in OOP course
Author-email: dim.chechulov@gmail.com
